{
	"$schema": "http://schema.management.azure.com/schemas/2015-01-01/deploymentTemplate.json#",
	"contentVersion": "1.0.0.0",
	"parameters": {
		"factoryName": {
			"type": "string",
			"metadata": "Data Factory name",
			"defaultValue": "dumarkovopenhackmdw"
		}
	},
	"variables": {
		"factoryId": "[concat('Microsoft.DataFactory/factories/', parameters('factoryName'))]"
	},
	"resources": [
		{
			"name": "[concat(parameters('factoryName'), '/incremental_cloudstreaming_transactions_to_adls')]",
			"type": "Microsoft.DataFactory/factories/pipelines",
			"apiVersion": "2018-06-01",
			"properties": {
				"description": "Copy new or updated rows only from database using external control table",
				"activities": [
					{
						"name": "LookupLastWaterMark",
						"description": "Retrieve the last high-watermark value stored in external control table",
						"type": "Lookup",
						"dependsOn": [],
						"policy": {
							"timeout": "7.00:00:00",
							"retry": 0,
							"retryIntervalInSeconds": 30
						},
						"userProperties": [],
						"typeProperties": {
							"source": {
								"type": "SqlSource",
								"sqlReaderQuery": {
									"value": "select @{pipeline().parameters.Control_Table_Column_Name} as WatermarkValue from @{pipeline().parameters.Control_Table_Table_Name}",
									"type": "Expression"
								}
							},
							"dataset": {
								"referenceName": "AzureSqlDatabaseExternal_ControlTable1",
								"type": "DatasetReference"
							}
						}
					},
					{
						"name": "LookupCurrentWaterMark",
						"description": "Retrieve  the current maximum value in watermark column of source data store",
						"type": "Lookup",
						"dependsOn": [],
						"policy": {
							"timeout": "7.00:00:00",
							"retry": 0,
							"retryIntervalInSeconds": 30
						},
						"userProperties": [],
						"typeProperties": {
							"source": {
								"type": "SqlSource",
								"sqlReaderQuery": {
									"value": "@concat('select MAX(',pipeline().parameters.Data_Source_WaterMarkColumn, ') as NewWatermarkValue from ',pipeline().parameters.Data_Source_Table_Name)",
									"type": "Expression"
								}
							},
							"dataset": {
								"referenceName": "AzureSqlDatabaseDataSource1",
								"type": "DatasetReference"
							}
						}
					},
					{
						"name": "DeltaCopyfromDB",
						"description": "Copy activity to use query to filter the delta data by > last high-watermark and <= current high-watermark from source database, and then only copy the changes to the destination store.",
						"type": "Copy",
						"dependsOn": [
							{
								"activity": "LookupCurrentWaterMark",
								"dependencyConditions": [
									"Succeeded"
								]
							},
							{
								"activity": "LookupLastWaterMark",
								"dependencyConditions": [
									"Succeeded"
								]
							}
						],
						"policy": {
							"timeout": "7.00:00:00",
							"retry": 0,
							"retryIntervalInSeconds": 30
						},
						"userProperties": [],
						"typeProperties": {
							"source": {
								"type": "SqlSource",
								"sqlReaderQuery": {
									"value": "select * from @{pipeline().parameters.Data_Source_Table_Name} where @{pipeline().parameters.Data_Source_WaterMarkColumn} > '@{activity('LookupLastWaterMark').output.firstRow.WatermarkValue}' and @{pipeline().parameters.Data_Source_WaterMarkColumn} <= '@{activity('LookupCurrentWaterMark').output.firstRow.NewWatermarkValue}'",
									"type": "Expression"
								}
							},
							"sink": {
								"type": "DelimitedTextSink"
							},
							"enableStaging": false,
							"dataIntegrationUnits": 0
						},
						"inputs": [
							{
								"referenceName": "AzureSqlDatabaseDataSource1",
								"type": "DatasetReference"
							}
						],
						"outputs": [
							{
								"referenceName": "DataDestination1",
								"type": "DatasetReference",
								"parameters": {
									"Data_Destination_Container": {
										"value": "@pipeline().parameters.Data_Destination_Container",
										"type": "Expression"
									},
									"Data_Destination_Directory": {
										"value": "@pipeline().parameters.Data_Destination_Directory",
										"type": "Expression"
									}
								}
							}
						]
					},
					{
						"name": "UpdateWaterMark",
						"description": "Stored procedure activity to store the new high-watermark value into external control table for delta data loading. ",
						"type": "SqlServerStoredProcedure",
						"dependsOn": [
							{
								"activity": "DeltaCopyfromDB",
								"dependencyConditions": [
									"Succeeded"
								]
							}
						],
						"policy": {
							"timeout": "7.00:00:00",
							"retry": 0,
							"retryIntervalInSeconds": 30
						},
						"userProperties": [],
						"typeProperties": {
							"storedProcedureName": "[[dbo].[control_table_transactions_update]",
							"storedProcedureParameters": {
								"wm": {
									"value": {
										"value": "@activity('LookupCurrentWaterMark').output.firstRow.NewWatermarkValue",
										"type": "Expression"
									},
									"type": "datetime"
								}
							}
						},
						"linkedServiceName": {
							"referenceName": "southridge_cloudstreaming",
							"type": "LinkedServiceReference"
						}
					}
				],
				"parameters": {
					"Data_Source_Table_Name": {
						"type": "String",
						"defaultValue": "dbo.transactions"
					},
					"Data_Source_WaterMarkColumn": {
						"type": "String",
						"defaultValue": "CreatedDate"
					},
					"Data_Destination_Container": {
						"type": "String",
						"defaultValue": "source_data"
					},
					"Data_Destination_Directory": {
						"type": "String",
						"defaultValue": "southridge/cloudstreaming/dbo"
					},
					"Control_Table_Table_Name": {
						"type": "String",
						"defaultValue": "control_table_transactions"
					},
					"Control_Table_Column_Name": {
						"type": "String",
						"defaultValue": "wm"
					}
				},
				"annotations": []
			},
			"dependsOn": [
				"[concat(variables('factoryId'), '/datasets/AzureSqlDatabaseExternal_ControlTable1')]",
				"[concat(variables('factoryId'), '/datasets/AzureSqlDatabaseDataSource1')]",
				"[concat(variables('factoryId'), '/datasets/DataDestination1')]"
			]
		},
		{
			"name": "[concat(parameters('factoryName'), '/AzureSqlDatabaseDataSource1')]",
			"type": "Microsoft.DataFactory/factories/datasets",
			"apiVersion": "2018-06-01",
			"properties": {
				"description": "Connection to your source data store.",
				"linkedServiceName": {
					"referenceName": "southridge_cloudstreaming",
					"type": "LinkedServiceReference"
				},
				"annotations": [],
				"type": "AzureSqlTable",
				"schema": [],
				"typeProperties": {
					"schema": "dbo",
					"table": "DataSourceTable"
				}
			},
			"dependsOn": []
		},
		{
			"name": "[concat(parameters('factoryName'), '/AzureSqlDatabaseExternal_ControlTable1')]",
			"type": "Microsoft.DataFactory/factories/datasets",
			"apiVersion": "2018-06-01",
			"properties": {
				"description": "External control table to store high water mark value.",
				"linkedServiceName": {
					"referenceName": "southridge_cloudstreaming",
					"type": "LinkedServiceReference"
				},
				"annotations": [],
				"type": "AzureSqlTable",
				"schema": [],
				"typeProperties": {
					"schema": "dbo",
					"table": "watermarktable"
				}
			},
			"dependsOn": []
		},
		{
			"name": "[concat(parameters('factoryName'), '/DataDestination1')]",
			"type": "Microsoft.DataFactory/factories/datasets",
			"apiVersion": "2018-06-01",
			"properties": {
				"description": "Connection to your destination data store.",
				"linkedServiceName": {
					"referenceName": "dumarkovopenhackmdw",
					"type": "LinkedServiceReference"
				},
				"parameters": {
					"Data_Destination_Container": {
						"type": "String"
					},
					"Data_Destination_Directory": {
						"type": "String"
					}
				},
				"annotations": [],
				"type": "DelimitedText",
				"typeProperties": {
					"location": {
						"type": "AzureBlobFSLocation",
						"folderPath": {
							"value": "@{dataset().Data_Destination_Directory}",
							"type": "Expression"
						},
						"fileSystem": {
							"value": "@{dataset().Data_Destination_Container}",
							"type": "Expression"
						}
					},
					"columnDelimiter": ",",
					"escapeChar": "\\",
					"firstRowAsHeader": true,
					"quoteChar": "\""
				},
				"schema": []
			},
			"dependsOn": []
		}
	]
}